{
  "description_cn": "刚体之间的碰撞检测，防止刚体相互穿透。支持弹性碰撞和摩擦。",
  "description_en": "Collision detection between rigid bodies, prevents interpenetration. Supports elastic collision and friction.",
  "images": [
    "rigidbody_collide_demo.gif"
  ],
  "video": "",
  "tags": ["碰撞", "刚体", "物理", "检测"],
  "parameters": [
    {
      "name": "Restitution",
      "cn": "弹性系数",
      "en": "Restitution",
      "default": 0.5,
      "desc_cn": "碰撞弹性，0为完全非弹性，1为完全弹性",
      "desc_en": "Collision restitution, 0 for inelastic, 1 for elastic"
    },
    {
      "name": "Friction",
      "cn": "摩擦系数",
      "en": "Friction",
      "default": 0.3,
      "desc_cn": "碰撞时的摩擦力",
      "desc_en": "Friction during collision"
    }
  ],
  "examples": [
    "rigidbody_collision_simulation.gh"
  ],
  "author": "Kangaroo Team",
  "version": "2.0",
  "lastUpdated": "2026-01-18"
}
